gpsdistance/__init__.py
gpsdistance-0.0.5.dist-info/LICENSE
gpsdistance-0.0.5.dist-info/METADATA
gpsdistance-0.0.5.dist-info/WHEEL
gpsdistance-0.0.5.dist-info/top_level.txt
gpsdistance-0.0.5.dist-info/RECORD
