Metadata-Version: 2.1
Name: gpsdistance
Version: 0.0.5
Summary: GPS distance between 2D and 3D
Home-page: https://github.com/krnick/gpsdistance
Author: SONG,JUN-WEI
Author-email: sungboss2004@gmail.com
License: MIT Licence
Keywords: distance,GPS
Platform: UNKNOWN
Classifier: Programming Language :: Python :: 3
Classifier: License :: OSI Approved :: MIT License
Classifier: Operating System :: OS Independent
